[[{"pubkey":"EgeWo2RT6FHUcj9qz4iCEZtd3qC2Sdd87sY7fzuwk2NS","account":{"accountType":14,"governance":"oN2Jg3uXFegVmAHLRRJwveYynBPCZfPV1MiWjE6f6m6","governingTokenMint":"DDAFjgfUBTUpRZP7WUEz6xpH7NcZwi1gc2MribpbtYgd","state":5,"tokenOwnerRecord":"ABLL2KasNsnJkZETEJ1LYpQ5j7JtwjX5DLYqo3m8A9sE","signatoriesCount":1,"signatoriesSignedOffCount":1,"descriptionLink":"","name":"Change Metadata","voteType":{"type":0},"options":[{"label":"Approve","voteWeight":"01","voteResult":1,"instructionsExecutedCount":2,"instructionsCount":2,"instructionsNextIndex":2}],"denyVoteWeight":"00","reserved1":0,"draftAt":"689ebfb2","signingOffAt":"689ebfb9","votingAt":"689ebfb9","votingAtSlot":"157774d4","votingCompletedAt":1755234248,"executingAt":"689ec026","closedAt":"689ec029","executionFlags":0,"maxVoteWeight":"01","voteThreshold":{"type":0,"value":51},"vetoVoteWeight":"00"},"owner":"GovER5Lthms3bLBqWub97yVrMmEogzX7xNjdXpPPCVZw"}]]