[[{"pubkey":"AEYkbLezMyKqcPzxnaoiYnb1UBCT1NDCdg94Xc9u1Xjj","account":{"accountType":14,"governance":"AofzDJonLEb2kqeynCbmf1Gy1j5yophnWxREuqMsfNu7","governingTokenMint":"CH5aX1P9Hn7DwMhqG25kPf8yigEuyR5mZdXGKwnh8YDK","state":5,"tokenOwnerRecord":"GLUwQaAgXF71QvuoNonay1vWAbaRqG2Mn3yw9XdmJ3PK","signatoriesCount":1,"signatoriesSignedOffCount":1,"descriptionLink":"","name":"Add council member HstSB…LDRt1","voteType":{"type":0},"options":[{"label":"Approve","voteWeight":"01","voteResult":1,"instructionsExecutedCount":1,"instructionsCount":1,"instructionsNextIndex":1}],"denyVoteWeight":"00","reserved1":0,"draftAt":"672780ce","signingOffAt":"672780cf","votingAt":"672780cf","votingAtSlot":"11d6ba48","votingCompletedAt":1730642212,"executingAt":"672781a2","closedAt":"672781a2","executionFlags":0,"maxVoteWeight":"01","voteThreshold":{"type":0,"value":51},"vetoVoteWeight":"00"},"owner":"GovER5Lthms3bLBqWub97yVrMmEogzX7xNjdXpPPCVZw"}]]