[[{"pubkey":"HXw9nkLDjPsDTwUvpD1eEhhxSJsBjSTJbz3bBJcoUJVk","account":{"accountType":14,"governance":"nau7FScPG1sP7pfokyYThLaPV3jbLu7KqHpjx2KeSs7","governingTokenMint":"7qEdQ5F9cGNLpAf3Z8VjDp6wGabJPmVxf8ePuAaDGanZ","state":5,"tokenOwnerRecord":"DPqPFWge3bEFh67iuvZiDiD86iY3JrVVMP2HsipSEoae","signatoriesCount":1,"signatoriesSignedOffCount":1,"descriptionLink":"","name":"Update Wallet Rules for “8C7VjtSvhmAgifyQT49ULCoCNKNsdoNArvGppSYqKfeT”","voteType":{"type":0},"options":[{"label":"Approve","voteWeight":"01","voteResult":1,"instructionsExecutedCount":1,"instructionsCount":1,"instructionsNextIndex":1}],"denyVoteWeight":"00","reserved1":0,"draftAt":"667c4f7c","signingOffAt":"667c4f7f","votingAt":"667c4f7f","votingAtSlot":"10573dbb","votingCompletedAt":1719422910,"executingAt":"667c4fc3","closedAt":"667c4fc3","executionFlags":0,"maxVoteWeight":"01","voteThreshold":{"type":0,"value":60},"vetoVoteWeight":"00"},"owner":"GovER5Lthms3bLBqWub97yVrMmEogzX7xNjdXpPPCVZw"},{"pubkey":"G5LvsgEJyVxT5481C4PGmSBeJ4TWN43bB1fKrMBqNn23","account":{"accountType":14,"governance":"nau7FScPG1sP7pfokyYThLaPV3jbLu7KqHpjx2KeSs7","governingTokenMint":"7qEdQ5F9cGNLpAf3Z8VjDp6wGabJPmVxf8ePuAaDGanZ","state":5,"tokenOwnerRecord":"DPqPFWge3bEFh67iuvZiDiD86iY3JrVVMP2HsipSEoae","signatoriesCount":1,"signatoriesSignedOffCount":1,"descriptionLink":"","name":"Update Realms Config for \"TestTest\"","voteType":{"type":0},"options":[{"label":"Approve","voteWeight":"01","voteResult":1,"instructionsExecutedCount":1,"instructionsCount":1,"instructionsNextIndex":1}],"denyVoteWeight":"00","reserved1":0,"draftAt":"667c4fef","signingOffAt":"667c4ff2","votingAt":"667c4ff2","votingAtSlot":"10573ec0","votingCompletedAt":1719422974,"executingAt":"667c5005","closedAt":"667c5005","executionFlags":0,"maxVoteWeight":"01","voteThreshold":{"type":0,"value":60},"vetoVoteWeight":"00"},"owner":"GovER5Lthms3bLBqWub97yVrMmEogzX7xNjdXpPPCVZw"}]]