[
  {
    "pubkey": "C1CtNQC4NKEZkK4NMfonskkNcz1ZwaV1hAMTQGox99eA",
    "account": {
      "accountType": 12,
      "proposal": "3QwueD9zhooJ14CSWcp6ZhqtMvELWDuP2Vr6fCuRpnDM",
      "governingTokenOwner": "Fywb7YDCXxtD7pNKThJ36CAtVe23dEeEPf7HqKzJs1VG",
      "isRelinquished": true,
      "voterWeight": "3592646051781",
      "vote": {
        "voteType": 0,
        "approveChoices": [
          {
            "rank": 0,
            "weightPercentage": 0
          },
          {
            "rank": 0,
            "weightPercentage": 100
          }
        ]
      }
    },
    "owner": "GovER5Lthms3bLBqWub97yVrMmEogzX7xNjdXpPPCVZw"
  },
  {
    "pubkey": "7sJ8w3J6Fhq5YcMJKzE4FntAuPRFa7kjxYu21qnsju7m",
    "account": {
      "accountType": 12,
      "proposal": "3QwueD9zhooJ14CSWcp6ZhqtMvELWDuP2Vr6fCuRpnDM",
      "governingTokenOwner": "Qrw6y2DiogvivGah9Dj9BuDu8Cr7qxCRUEh63Z1dmpv",
      "isRelinquished": true,
      "voterWeight": "8241476096812",
      "vote": {
        "voteType": 0,
        "approveChoices": [
          {
            "rank": 0,
            "weightPercentage": 100
          },
          {
            "rank": 0,
            "weightPercentage": 100
          }
        ]
      }
    },
    "owner": "GovER5Lthms3bLBqWub97yVrMmEogzX7xNjdXpPPCVZw"
  },
  {
    "pubkey": "F87eQXR4GzicfEGDNqwMXoSNzhQ2bRS3hUhUTUdGyNYr",
    "account": {
      "accountType": 12,
      "proposal": "3QwueD9zhooJ14CSWcp6ZhqtMvELWDuP2Vr6fCuRpnDM",
      "governingTokenOwner": "ATivaSMnHMPUqz81rSzm2ceh6zRYqbhBKx3cMcChqBmK",
      "isRelinquished": true,
      "voterWeight": "17075000000",
      "vote": {
        "voteType": 0,
        "approveChoices": [
          {
            "rank": 0,
            "weightPercentage": 0
          },
          {
            "rank": 0,
            "weightPercentage": 100
          }
        ]
      }
    },
    "owner": "GovER5Lthms3bLBqWub97yVrMmEogzX7xNjdXpPPCVZw"
  },
  {
    "pubkey": "GyqqqzqhDGxQgSxUUJLGeZKPw5dtG7UF7ji9BLi4obob",
    "account": {
      "accountType": 12,
      "proposal": "3QwueD9zhooJ14CSWcp6ZhqtMvELWDuP2Vr6fCuRpnDM",
      "governingTokenOwner": "CinHb6Xt2PnqKUkmhRo9hwUkixCcsH1uviuQqaTxwT9i",
      "isRelinquished": true,
      "voterWeight": "4295229143496",
      "vote": {
        "voteType": 0,
        "approveChoices": [
          {
            "rank": 0,
            "weightPercentage": 100
          },
          {
            "rank": 0,
            "weightPercentage": 100
          }
        ]
      }
    },
    "owner": "GovER5Lthms3bLBqWub97yVrMmEogzX7xNjdXpPPCVZw"
  }
]